py_awesome/__init__.py
py_awesome/application.py
py_awesome/gen.py
py_awesome/assets/blank_check_box.png
py_awesome/assets/iciel_pony.ttf
py_awesome/assets/selected_check_box.png
py_awesome/core/assets.py
py_awesome/core/audio_manager.py
py_awesome/core/local_strorage.py
py_awesome/core/localization.py
py_awesome/core/logger.py
py_awesome/core/singleton.py
py_awesome/game/animations/animation.py
py_awesome/game/animations/animation_manager.py
py_awesome/game/entity/entity.py
py_awesome/game/entity/entity_group.py
py_awesome/game/entity/texture.py
py_awesome/game/state/base_state.py
py_awesome/game/state/state_machine.py
py_awesome/game/widget/button.py
py_awesome/game/widget/check_box.py
py_awesome/game/widget/health_bar.py
py_awesome/game/widget/image.py
py_awesome/game/widget/text.py
py_awesome/game/widget/widget.py
py_awesome/game/widget/widget_group.py
py_awesome/local_storage/local.json
py_awesome/utils/clock.py
py_awesome/utils/media_query.py
py_awesome/utils/vector2.py
py_awesome-0.4.1.dist-info/METADATA
py_awesome-0.4.1.dist-info/WHEEL
py_awesome-0.4.1.dist-info/entry_points.txt
py_awesome-0.4.1.dist-info/top_level.txt
py_awesome-0.4.1.dist-info/RECORD
