Metadata-Version: 2.1
Name: py-awesome
Version: 0.4.1
Summary: Awesome Python Package to build games
Home-page: https://github.com/alexcao194/py_awesome
Download-URL: https://github.com/alexcao194/py_awesome
Author: Alexcao
Author-email: alexcao194@gmail.com
Maintainer: Alexcao
Maintainer-email: alexcao194@gmail.com
License: MIT
Classifier: Development Status :: 4 - Beta
Classifier: License :: OSI Approved :: MIT License
Classifier: Topic :: Software Development :: Libraries :: Python Modules
Classifier: Intended Audience :: Developers
Classifier: Programming Language :: Python :: 2
Classifier: Programming Language :: Python :: 2.7
Classifier: Programming Language :: Python :: 3
Classifier: Programming Language :: Python :: 3.5
Classifier: Programming Language :: Python :: 3.6
Classifier: Programming Language :: Python :: 3.7
Classifier: Programming Language :: Python :: Implementation
Requires-Python: !=3.0.*,!=3.1.*,!=3.2.*,!=3.3.*,!=3.4.*,<4,>=2.7
Requires-Dist: pygame
